{
  "request_staff_info": {
    "precision": 1.0,
    "recall": 1.0,
    "f1-score": 1.0,
    "support": 2
  },
  "deny": {
    "precision": 1.0,
    "recall": 0.8333333333333334,
    "f1-score": 0.9090909090909091,
    "support": 6
  },
  "action_button_semester": {
    "precision": 1.0,
    "recall": 0.5,
    "f1-score": 0.6666666666666666,
    "support": 4
  },
  "action_uni_contact_loc_info": {
    "precision": 1.0,
    "recall": 1.0,
    "f1-score": 1.0,
    "support": 1
  },
  "[Spring]{\"entity\": \"period\", \"value\": \"spring\"}": {
    "precision": 0.0,
    "recall": 0.0,
    "f1-score": 0.0,
    "support": 1
  },
  "utter_goodbye": {
    "precision": 1.0,
    "recall": 1.0,
    "f1-score": 1.0,
    "support": 8
  },
  "utter_greet": {
    "precision": 1.0,
    "recall": 1.0,
    "f1-score": 1.0,
    "support": 8
  },
  "action_resetSlots": {
    "precision": 1.0,
    "recall": 1.0,
    "f1-score": 1.0,
    "support": 10
  },
  "[undergrad]{\"entity\": \"grad_studies_type\", \"value\": \"PPS\"}": {
    "precision": 1.0,
    "recall": 1.0,
    "f1-score": 1.0,
    "support": 4
  },
  "action_uni_staff_info": {
    "precision": 1.0,
    "recall": 1.0,
    "f1-score": 1.0,
    "support": 2
  },
  "request_announcements": {
    "precision": 1.0,
    "recall": 1.0,
    "f1-score": 1.0,
    "support": 1
  },
  "goodbye": {
    "precision": 1.0,
    "recall": 0.8333333333333334,
    "f1-score": 0.9090909090909091,
    "support": 6
  },
  "[2021](academic_year)": {
    "precision": 0.8,
    "recall": 1.0,
    "f1-score": 0.888888888888889,
    "support": 4
  },
  "request_contact_loc_info": {
    "precision": 1.0,
    "recall": 1.0,
    "f1-score": 1.0,
    "support": 1
  },
  "action_button_year": {
    "precision": 0.0,
    "recall": 0.0,
    "f1-score": 0.0,
    "support": 4
  },
  "request_exam_schedule": {
    "precision": 0.0,
    "recall": 0.0,
    "f1-score": 0.0,
    "support": 1
  },
  "request_class_schedule": {
    "precision": 0.6666666666666666,
    "recall": 1.0,
    "f1-score": 0.8,
    "support": 2
  },
  "action_uni_class_schedule": {
    "precision": 1.0,
    "recall": 1.0,
    "f1-score": 1.0,
    "support": 4
  },
  "[Sprinf]{\"entity\": \"semester\", \"value\": \"spring\"}": {
    "precision": 0.0,
    "recall": 0.0,
    "f1-score": 0.0,
    "support": 2
  },
  "inform_programme": {
    "precision": 1.0,
    "recall": 1.0,
    "f1-score": 1.0,
    "support": 4
  },
  "action_UniPal_services": {
    "precision": 0.9090909090909091,
    "recall": 1.0,
    "f1-score": 0.9523809523809523,
    "support": 10
  },
  "inform_semester": {
    "precision": 0.75,
    "recall": 1.0,
    "f1-score": 0.8571428571428571,
    "support": 3
  },
  "request_exams_schedule": {
    "precision": 0.0,
    "recall": 0.0,
    "f1-score": 0.0,
    "support": 1
  },
  "action_correct_examform_slots": {
    "precision": 1.0,
    "recall": 0.875,
    "f1-score": 0.9333333333333333,
    "support": 8
  },
  "inform_period": {
    "precision": 0.0,
    "recall": 0.0,
    "f1-score": 0.0,
    "support": 1
  },
  "None": {
    "precision": 0.0,
    "recall": 0.0,
    "f1-score": 0.0,
    "support": 3
  },
  "action_uni_announcements": {
    "precision": 1.0,
    "recall": 1.0,
    "f1-score": 1.0,
    "support": 1
  },
  "affirm": {
    "precision": 1.0,
    "recall": 1.0,
    "f1-score": 1.0,
    "support": 6
  },
  "[Theatina](user_name)": {
    "precision": 1.0,
    "recall": 1.0,
    "f1-score": 1.0,
    "support": 1
  },
  "[undergraduate]{\"entity\": \"grad_studies_type\", \"value\": \"PPS\"}": {
    "precision": 1.0,
    "recall": 1.0,
    "f1-score": 1.0,
    "support": 1
  },
  "[Spring]{\"entity\": \"semester\", \"value\": \"spring\"}": {
    "precision": 0.5,
    "recall": 1.0,
    "f1-score": 0.6666666666666666,
    "support": 1
  },
  "action_button_programme": {
    "precision": 1.0,
    "recall": 0.75,
    "f1-score": 0.8571428571428571,
    "support": 4
  },
  "utter_further_action": {
    "precision": 1.0,
    "recall": 1.0,
    "f1-score": 1.0,
    "support": 8
  },
  "action_listen": {
    "precision": 1.0,
    "recall": 1.0,
    "f1-score": 1.0,
    "support": 46
  },
  "[tina](user_name)": {
    "precision": 1.0,
    "recall": 1.0,
    "f1-score": 1.0,
    "support": 2
  },
  "greet": {
    "precision": 1.0,
    "recall": 1.0,
    "f1-score": 1.0,
    "support": 8
  },
  "inform_year": {
    "precision": 1.0,
    "recall": 1.0,
    "f1-score": 1.0,
    "support": 4
  },
  "[2](num_of_announcements)": {
    "precision": 1.0,
    "recall": 1.0,
    "f1-score": 1.0,
    "support": 1
  },
  "micro avg": {
    "precision": 0.9705882352941176,
    "recall": 0.8967391304347826,
    "f1-score": 0.9322033898305084,
    "support": 184
  },
  "macro avg": {
    "precision": 0.7796251993620414,
    "recall": 0.7839912280701755,
    "f1-score": 0.7747474747474747,
    "support": 184
  },
  "weighted avg": {
    "precision": 0.9096426218708827,
    "recall": 0.8967391304347826,
    "f1-score": 0.8988503042850868,
    "support": 184
  },
  "accuracy": 0.8967391304347826,
  "conversation_accuracy": {
    "accuracy": 0.125,
    "correct": 1,
    "with_warnings": 0,
    "total": 8
  }
}